[
  {
    "name": "Aravind Pitchika",
    "business": "Om sri parasara jyotishya vaastu nilayam",
    "category": "Architecture & Engineering > Vaastu Consultant",
    "phone": null,
    "my_business": null,
    "top_product": null,
    "ideal_referral": null,
    "top_problem_solved": null,
    "my_favourite_bni_story": null,
    "chapter": "BNI Dazzlers"
  },
  {
    "name": "Borana Harish Kumar",
    "business": "Plywood Home",
    "category": "Construction > Cabinet Maker",
    "phone": null,
    "my_business": null,
    "top_product": null,
    "ideal_referral": null,
    "top_problem_solved": null,
    "my_favourite_bni_story": null,
    "chapter": "BNI Dazzlers"
  },
  {
    "name": "Buchi raju gollapudi",
    "business": "sri lakshmi narasimha petro station",
    "category": "Retail > Fuels",
    "phone": null,
    "my_business": null,
    "top_product": null,
    "ideal_referral": null,
    "top_problem_solved": null,
    "my_favourite_bni_story": null,
    "chapter": "BNI Dazzlers"
  },
  {
    "name": "Ganesh Prasad Chebrolu",
    "business": "Zeepee Photography",
    "category": "Advertising & Marketing > Photographer",
    "phone": null,
    "my_business": null,
    "top_product": null,
    "ideal_referral": null,
    "top_problem_solved": null,
    "my_favourite_bni_story": null,
    "chapter": "BNI Dazzlers"
  },
  {
    "name": "Harini Garbham",
    "business": "Sri Chaitanya Cosmetic Center",
    "category": "Health & Wellness > Health & Wellness (Other)",
    "phone": null,
    "my_business": null,
    "top_product": null,
    "ideal_referral": null,
    "top_problem_solved": null,
    "my_favourite_bni_story": null,
    "chapter": "BNI Dazzlers"
  },
  {
    "name": "Krishna Polisetty",
    "business": "Kohinoor Paints",
    "category": "Retail > Paint Retail",
    "phone": null,
    "my_business": null,
    "top_product": null,
    "ideal_referral": null,
    "top_problem_solved": null,
    "my_favourite_bni_story": null,
    "chapter": "BNI Dazzlers"
  },
  {
    "name": "Naresh Singamsetti",
    "business": "Naresh consultancy",
    "category": "Real Estate Services > Buying Agent",
    "phone": null,
    "my_business": null,
    "top_product": null,
    "ideal_referral": null,
    "top_problem_solved": null,
    "my_favourite_bni_story": null,
    "chapter": "BNI Dazzlers"
  },
  {
    "name": "Raja Rao Talluri",
    "business": "RR Associates",
    "category": "Finance & Insurance > Business Financing",
    "phone": null,
    "my_business": null,
    "top_product": null,
    "ideal_referral": null,
    "top_problem_solved": null,
    "my_favourite_bni_story": null,
    "chapter": "BNI Dazzlers"
  },
  {
    "name": "Rajesh S.B Payasam",
    "business": "LIC & STAR",
    "category": "Finance & Insurance > Life and Disability Insurance",
    "phone": null,
    "my_business": null,
    "top_product": null,
    "ideal_referral": null,
    "top_problem_solved": null,
    "my_favourite_bni_story": null,
    "chapter": "BNI Dazzlers"
  },
  {
    "name": "Ranjith Kumar Kanaparthi",
    "business": "Zibe Luxe Kakinada by GRT Hotels",
    "category": "Event & Business Service > Hotel",
    "phone": null,
    "my_business": null,
    "top_product": null,
    "ideal_referral": null,
    "top_problem_solved": null,
    "my_favourite_bni_story": null,
    "chapter": "BNI Dazzlers"
  },
  {
    "name": "Sameer Kumar Dwarampudi",
    "business": "Kusuma Satya Convention Hall",
    "category": "Event & Business Service > Event Venue/Room Rental",
    "phone": null,
    "my_business": null,
    "top_product": "The biggest indoor space for conventions in the district",
    "ideal_referral": "Corporate Company Connects",
    "top_problem_solved": null,
    "my_favourite_bni_story": null,
    "chapter": "BNI Dazzlers"
  },
  {
    "name": "Sanjeeva Rao Yalla",
    "business": "D DESTINATION",
    "category": "Retail > Clothing & Accessories Retailer",
    "phone": null,
    "my_business": null,
    "top_product": null,
    "ideal_referral": null,
    "top_problem_solved": null,
    "my_favourite_bni_story": null,
    "chapter": "BNI Dazzlers"
  },
  {
    "name": "Sirajuddin Siraj Mohammed",
    "business": "I2I opticals",
    "category": "Health & Wellness > Optician",
    "phone": null,
    "my_business": null,
    "top_product": null,
    "ideal_referral": null,
    "top_problem_solved": null,
    "my_favourite_bni_story": null,
    "chapter": "BNI Dazzlers"
  },
  {
    "name": "Srinivas Arigela",
    "business": "Digital Sound Systems",
    "category": "Retail > Home Theatres",
    "phone": null,
    "my_business": null,
    "top_product": null,
    "ideal_referral": null,
    "top_problem_solved": null,
    "my_favourite_bni_story": null,
    "chapter": "BNI Dazzlers"
  },
  {
    "name": "Suryanarayana Murthy B",
    "business": "Bonagiri Chits",
    "category": "Finance & Insurance > Financial Investments",
    "phone": null,
    "my_business": null,
    "top_product": null,
    "ideal_referral": null,
    "top_problem_solved": null,
    "my_favourite_bni_story": null,
    "chapter": "BNI Dazzlers"
  },
  {
    "name": "VINEEL PURAM",
    "business": "SANTHI PLASTICS",
    "category": "Manufacturing > Rubber & Plastic",
    "phone": null,
    "my_business": null,
    "top_product": "Highest diameter of pvc pipes",
    "ideal_referral": null,
    "top_problem_solved": null,
    "my_favourite_bni_story": null,
    "chapter": "BNI Dazzlers"
  }
]